cxbind/__about__.py
cxbind/__init__.py
cxbind/__main__.py
cxbind/actions.py
cxbind/builder.py
cxbind/builder_context.py
cxbind/cu.py
cxbind/entry.py
cxbind/generator.py
cxbind/generator_config.py
cxbind/node.py
cxbind/node_cls_map.py
cxbind/runner.py
cxbind/yaml.py
cxbind/cli/__init__.py
cxbind/include/cxbind/cxbind.h
cxbind/node_builder/__init__.py
cxbind/node_builder/class_builder.py
cxbind/node_builder/ctor_builder.py
cxbind/node_builder/enum_builder.py
cxbind/node_builder/field_builder.py
cxbind/node_builder/function_base_builder.py
cxbind/node_builder/function_builder.py
cxbind/node_builder/method_builder.py
cxbind/node_builder/node_builder.py
cxbind/node_builder/node_builder_cls_map.py
cxbind/node_builder/struct_base_builder.py
cxbind/node_builder/struct_builder.py
cxbind/node_builder/typedef_builder.py
cxbind/share/cmake/cxbind/cxbindConfig.cmake
cxbind/share/cmake/cxbind/cxbindConfigVersion.cmake
cxbind/share/cmake/cxbind/cxbindTargets.cmake
cxbind/share/cmake/cxbind/cxbindTools.cmake
cxbind/templates/check_return.cpp
cxbind-0.3.dist-info/METADATA
cxbind-0.3.dist-info/WHEEL
cxbind-0.3.dist-info/entry_points.txt
cxbind-0.3.dist-info/licenses/LICENSE
cxbind-0.3.dist-info/RECORD
