Metadata-Version: 2.1
Name: cxbind
Version: 0.3
Summary: pybind11 binding generator
Project-URL: homepage, https://github.com/crunge/cxbind
Project-URL: documentation, https://crungelab.github.io/cxbind/
Project-URL: repository, https://github.com/crungelab/cxbind
Project-URL: changelog, https://github.com/crungelab/cxbind/blob/main/CHANGELOG.md
Author-email: Kurtis Fields <kurtisfields@gmail.com>
License: MIT License
License-File: LICENSE
Classifier: Development Status :: 4 - Beta
Classifier: Programming Language :: Python
Classifier: Programming Language :: Python :: 3.8
Classifier: Programming Language :: Python :: 3.9
Classifier: Programming Language :: Python :: 3.10
Classifier: Programming Language :: Python :: 3.11
Classifier: Programming Language :: Python :: Implementation :: CPython
Classifier: Programming Language :: Python :: Implementation :: PyPy
Requires-Python: >=3.8
Requires-Dist: clang==15.0.7
Requires-Dist: click~=8.1.7
Requires-Dist: jinja2~=3.1.2
Requires-Dist: loguru~=0.7.2
Requires-Dist: pydantic~=2.5.3
Requires-Dist: pyyaml~=6.0.1
Provides-Extra: dev
Requires-Dist: black~=22.12.0; extra == 'dev'
Provides-Extra: test
Requires-Dist: pytest~=7.2.1; extra == 'test'
